{
"zhubo": [
{ "address":"rtmp://liveplay.guojianglive.com/live/9180_1050152","img":"http://static.guojiang.tv/app/upload/2019_08_17/6e84905fedeac7c11af52bd63b7e6b34.jpg","title":"%3F%3F\u5DE8\u87F9\u5EA7\u306E\u4E03\u516C\u5B50"},{ "address":"http://rtazy.ke62w.cn/live/896803463_64f9f529a6fa7e46a020.flv","img":"http://static.guojiang.tv/app/upload/2019_08_12/dedc5d0aa131627df2e57fad81a5c577.jpg","title":"%3F%3F\u94B0\u4E00\u513F%3F%3F"},{ "address":"rtmp://liveplay.guojianglive.com/live/9180_1207913","img":"http://static.guojiang.tv/app/upload/2019_08_20/4b3b1bbe390179639c9347b8a092351d.jpg","title":"\u516E\u516E%3F%3F\u665A\u4E0A\u64AD"},{ "address":"rtmp://liveplay.guojianglive.com/live/9180_1111463","img":"http://static.guojiang.tv/app/upload/2019_08_10/88cce6a585af27510181a98fc600b8cf.jpg","title":"H%3F%3F\u9752\u9752\u55D3\u5B50\u75BC\u4F112"},{ "address":"rtmp://liveplay.guojianglive.com/live/9180_1157372","img":"http://static.guojiang.tv/app/upload/2019_08_20/f3a7d39dd9592d5eb672ffbf179d5700.jpg","title":"%3F%3F%20%3F\u5C0F\u5A18\u5B50"},{ "address":"rtmp://liveplay.guojianglive.com/live/9180_1107833","img":"http://static.guojiang.tv/app/upload/2018_11_14/1719d26791c029b0cf408d9990a3d52f.jpg","title":"\u5305\u5927\u7237"},{ "address":"rtmp://liveplay.guojianglive.com/live/9180_1063975","img":"http://static.guojiang.tv/app/upload/2019_08_20/38e34e5fe3873d89f16b3578301af566.jpg","title":"\u7396\u513F\u611F\u6069\u9047\u89C1%3F%3F"},{ "address":"http://pullws.styl555.com/live/80421e11a82445eabd6b97091025b9e9_480.flv","img":"https://p.best31w.com/public/attachment/201907/252331/1563622705963.png","title":"2019\u8D5E*\u5546\u3000\u3000\u3000\u3000\u3000\u3000\u3000\u300088"},{ "address":"rtmp://liveplay.guojianglive.com/live/9180_1255474","img":"http://static.guojiang.tv/app/upload/2019_08_15/4ad41392cc33949c0cb9fcb4ef199c85.jpg","title":"\u5C0F\u5189%3F%3F23\u53F7\u6EE1\u6708"},{ "address":"rtmp://liveplay.guojianglive.com/live/9180_1218700","img":"http://static.guojiang.tv/app/upload/2019_08_17/766e9ddf4c36f60362e3c32afe24ff3e.jpg","title":"\u53EF\u5FC3%3F%3F\u78E8\u4EBA\u7CBE"},{ "address":"rtmp://liveplay.guojianglive.com/live/9180_1215175","img":"http://static.guojiang.tv/app/upload/2019_08_06/a0c93eff2deeb218519eb5781938394d.jpg","title":"%3F\u661F\u598D%20\u6C42\u5B88\u62A4%3F"},{ "address":"rtmp://liveplay.guojianglive.com/live/9180_1153181","img":"http://static.guojiang.tv/app/upload/2019_08_19/c68686fc4918a0b172a43ed8b296ba19.jpg","title":"\u56FD\u4EA7%3F%3F\u5C0F\u4ED9\u5973%3F%3F"},{ "address":"rtmp://liveplay.guojianglive.com/live/9180_1094794","img":"http://static.guojiang.tv/app/upload/2019_08_12/63395ea3924a505eb8fbbdc5baef4e43.jpg","title":"%3F\u4E39\u4E39%3F\u6C42\u5BA0\u7231"},{ "address":"rtmp://liveplay.guojianglive.com/live/9180_847708","img":"http://static.guojiang.tv/app/upload/2017_11_20/3875c3f462668dda919a19ea3e9867ae.jpg","title":"\u51EF\u4F26\u4E36\u91CD%3F\u51FA\u53D1"},{ "address":"rtmp://liveplay.guojianglive.com/live/9180_1224671","img":"http://static.guojiang.tv/app/upload/2019_06_18/1f5207e68e50b0847ff5dea0ef474011.jpg","title":"\u5927\u599E\u5B50"},{ "address":"rtmp://liveplay.guojianglive.com/live/9180_1253871","img":"http://static.guojiang.tv/app/upload/2019_08_06/4b362c84a98bb6a4e04a9b9d26ed7fab.jpg","title":"\u5B9D\u8D1Dgirl"},{ "address":"rtmp://liveplay.guojianglive.com/live/9180_1199628","img":"http://static.guojiang.tv/app/upload/2019_08_06/b2cc654cd9906750fdc2be28d9d9fde5.jpg","title":"%3F%3F\u5C0F\u7C73%3F%3F\u6C42\u5B88\u62A4"},{ "address":"rtmp://liveplay.guojianglive.com/live/9180_1035744","img":"http://static.guojiang.tv/app/upload/2019_08_17/e06dfb5ed02285d1325b4ef409f333f2.jpg","title":"\u9C7C\u5B9D\u5B9D\u5C0F\u9614\u7231%3F%3F"},{ "address":"rtmp://liveplay.guojianglive.com/live/9180_326812","img":"http://static.guojiang.tv/app/upload/2019_08_14/4551a9adf1bb8993a30672413a459b9e.jpg","title":"\u5C0F%3F%3F\u6843\u82B1%3F%3F\u611F\u6069"},{ "address":"rtmp://liveplay.guojianglive.com/live/9180_1251113","img":"http://static.guojiang.tv/app/upload/2019_08_18/70f79d39d55a048295812399da779ab8.jpg","title":"\u672A\u6765%3F%3F%3F%3F"}]
}