{"zhubo": [{"address": "rtmp://liveplay.guojianglive.com/live/9180_1255474", "img": "http://static.guojiang.tv/app/upload/2019_08_15/4ad41392cc33949c0cb9fcb4ef199c85.jpg", "title": "\u5c0f\u5189%3F%3F\u4eca\u5929\u6ee1\u6708\u5566"}, {"address": "rtmp://liveplay.guojianglive.com/live/9180_1055968", "img": "http://static.guojiang.tv/app/upload/2019_06_23/a1a484ce91105b984d4022294583b6c9.jpg", "title": "%3F%3F\u7c98\u4eba\u7684\u599e\u599e"}, {"address": "rtmp://liveplay.guojianglive.com/live/9180_168619", "img": "http://static.guojiang.tv/app/upload/2019_08_04/af1f7ce0a94c625e84c26931e1b80edb.jpg", "title": "\u5e05%3F%3F%3F\u5144\u5f1f"}, {"address": "https://s3.pstatp.com/aweme/resource/web/static/image/index/tvc-v3_4138031.mp4", "img": "http://static.guojiang.tv/app/upload/2019_06_14/ad4e86a7891ac735432ee163db1c9c7d.jpg", "title": "%3F%3F\u7cef\u7cef%3F%3F."}, {"address": "rtmp://liveplay.guojianglive.com/live/9180_1266869", "img": "http://static.guojiang.tv/app/upload/2019_08_20/d7168617c5fe2a0d2fdea200610ad132.jpg", "title": "Plus\u5f88ok%3F%3F"}, {"address": "rtmp://liveplay.guojianglive.com/live/9180_994099", "img": "http://static.guojiang.tv/app/upload/2019_08_22/ad32bfb9cfd0026a74663a7ce140c809.jpg", "title": "\u6bd2\u59ae%28\u968f\u7f18\u5c31\u597d%29"}, {"address": "rtmp://liveplay.guojianglive.com/live/9180_1248700", "img": "http://static.guojiang.tv/app/upload/2019_07_11/132d71fe5c0d4d34e2b013d5c20be138.jpg", "title": "\u65b0\u4eba%3F\u6696\u6b23%3F"}, {"address": "rtmp://liveplay.guojianglive.com/live/9180_1213788", "img": "http://static.guojiang.tv/app/upload/2019_08_14/aec3ffbceed77dc78f5f4c01d9718550.jpg", "title": "%3F%3F\u4ee5\u8f69\u4e94\u4e07\u4eba\u89c2\u770b"}, {"address": "rtmp://liveplay.guojianglive.com/live/9180_1242443", "img": "http://static.guojiang.tv/app/upload/2019_08_16/756c254d0968643081b83f515aa69d22.jpg", "title": "\u5999\u5999\uff5e\u745c\u4f3d\u5065\u8eab"}, {"address": "rtmp://liveplay.guojianglive.com/live/9180_931576", "img": "http://static.guojiang.tv/app/upload/2019_07_23/1806991e51c21566ab6000bbbe648a17.jpg", "title": "\u9047\u89c1%3F%3F\u4f1a\u6709\u597d\u8fd0\u6c14"}, {"address": "rtmp://liveplay.guojianglive.com/live/9180_1266299", "img": "http://static.guojiang.tv/app/upload/2019_08_14/6c16be9ec1cb8815afc23ccb9cfcb61b.jpg", "title": "\u5b63\u51c9\u751f%3F%3F\u5f00\u5b66\u5012\u8ba1\u65f6%28"}, {"address": "rtmp://liveplay.guojianglive.com/live/9180_1199628", "img": "http://static.guojiang.tv/app/upload/2019_08_06/b2cc654cd9906750fdc2be28d9d9fde5.jpg", "title": "%3F%3F\u5c0f\u7c73%3F%3F\u6c42\u5b88\u62a4"}, {"address": "rtmp://liveplay.guojianglive.com/live/9180_1218700", "img": "http://static.guojiang.tv/app/upload/2019_08_21/6d3d87602ffb0f27fc6881bd2bdd5cc2.jpg", "title": "\u5c0f%20%20%20\u7c73%20%20%20%20\u7c92"}, {"address": "rtmp://liveplay.guojianglive.com/live/9180_1002803", "img": "http://static.guojiang.tv/app/upload/2019_06_11/6d27a0e0bfce9e6f2574fcd427b713d7.jpg", "title": "%3F%3F\u8d1d\u513f%3F%3F%3F%3F%3F%3F"}, {"address": "rtmp://liveplay.guojianglive.com/live/9180_1083629", "img": "http://static.guojiang.tv/app/upload/2019_07_31/ccb94dbcd1621c41f6956e2ea621fd88.jpg", "title": "\u840c\u96ea"}, {"address": "rtmp://liveplay.guojianglive.com/live/9180_1260466", "img": "http://static.guojiang.tv/app/upload/2019_08_12/af48ab5dcd94182761cd825b38614009.jpg", "title": "\u5e7a%3F%3F\u59b9%3F%3F\u65b0\u4eba"}, {"address": "rtmp://liveplay.guojianglive.com/live/9180_975669", "img": "http://static.guojiang.tv/app/upload/2019_07_23/8d0a8cc7b260fdeb143145bd4d20ef95.jpg", "title": "%3F\u5708\u5708%3F%3F%3F%3F%3F%3F%3F"}, {"address": "rtmp://liveplay.guojianglive.com/live/9180_1241773", "img": "http://static.guojiang.tv/app/upload/2019_08_20/9a6d03314a07f7359b90ae8726e7de37.jpg", "title": "\uff1a\u2295\u6824\u9ede\u2121"}, {"address": "rtmp://liveplay.guojianglive.com/live/9180_1268989", "img": "http://static.guojiang.tv/app/upload/2019_08_17/d563bcbc2590aea3f4fb4f610e5b8d79.jpg", "title": "\u65b0\u4eba\uff0c\u4e1c\u5317\u7389\u513f"}, {"address": "rtmp://liveplay.guojianglive.com/live/9180_1243522", "img": "http://static.guojiang.tv/app/upload/2019_08_03/0a85b5d3c708b50c0ab3222a289a5861.jpg", "title": "\u827a\u51fd\u5927\u5634\u7f8e\u4eba\u56de\u5f52%3F%3F"}]}