{"zhubo": [{"address": "rtmp://liveplay.guojianglive.com/live/9180_1019921", "img": "http://static.guojiang.tv/app/upload/2019_07_16/9c1573d2ea944ec1bf04deb7bffc712b.jpg", "title": "Miss%20%20%20Q%3F%3F"}, {"address": "rtmp://liveplay.guojianglive.com/live/9180_1209749", "img": "http://static.guojiang.tv/app/upload/2019_07_30/e567ced8bebf6e62a65840840622076e.jpg", "title": "\u9752\u4e18\u5973\u5e1d.\u99a8\u5b9d\u6c42\u5b88\u62a4"}, {"address": "rtmp://liveplay.guojianglive.com/live/9180_1214364", "img": "http://static.guojiang.tv/app/upload/2019_08_20/3f6ab11ab915405f51debe7295b3b8f0.jpg", "title": "\u725b\u5976\u55b5"}, {"address": "https://s3.pstatp.com/aweme/resource/web/static/image/index/tvc-v3_4138031.mp4", "img": "http://static.guojiang.tv/app/upload/2019_08_07/1dc08605f13309eecec50ab838f81ade.jpg", "title": "\u6e29\u59ae%3F%3F"}, {"address": "rtmp://liveplay.guojianglive.com/live/9180_1256314", "img": "http://static.guojiang.tv/app/upload/2019_08_09/e9946a0aeb76ee543e7f199b542e3bbe.jpg", "title": "%3F%3F\u5c0f\u55b5%3F\u6f5e\u5b9d"}, {"address": "rtmp://liveplay.guojianglive.com/live/9180_1125589", "img": "http://static.guojiang.tv/app/upload/2019_08_09/8fe5dbbeed48766cee44c1285917af03.png", "title": "\u793e\u4f1a\u7476\u611f\u8c22\u966a\u4f34%3F%3F"}, {"address": "rtmp://liveplay.guojianglive.com/live/9180_1191014", "img": "http://static.guojiang.tv/app/upload/2019_07_27/780cfce9b771dafade3bd04e904fd49f.jpg", "title": "\u4e50\u5b9d\u5b9d%3F%3F%3F%3F"}, {"address": "rtmp://liveplay.guojianglive.com/live/9180_1118765", "img": "http://static.guojiang.tv/app/upload/2019_03_12/f0dfb64f69b03956753241cd6d77e37c.jpg", "title": "%3F%3F\u5929\u4f7f\u5b9d\u5b9d%3F%3F%3F%3F"}, {"address": "rtmp://liveplay.guojianglive.com/live/9180_1265652", "img": "http://static.guojiang.tv/app/upload/2019_08_14/a6e49932869d9009a24c2cd6ff3b20c6.jpg", "title": "\u9876\u5c16\u5973\u56e21"}, {"address": "rtmp://liveplay.guojianglive.com/live/9180_1134874", "img": "http://static.guojiang.tv/app/upload/2019_08_17/781271358fa1c74893a3bf9f4052f73a.jpg", "title": "\u5c0f\u9cb8\u9c7c%3F%3F%3F%3F"}, {"address": "rtmp://liveplay.guojianglive.com/live/9180_1234977", "img": "http://static.guojiang.tv/app/upload/2019_08_16/1513de709e5052a6a8bccbf86bf4d101.jpg", "title": "%3F%3F\u732b\u67d2%20%3F%3F"}, {"address": "rtmp://liveplay.guojianglive.com/live/9180_1189298", "img": "http://static.guojiang.tv/app/upload/2019_08_18/e82c4a18d7d4080b67524abd3cc47fc4.jpg", "title": "%3F%3F%B7\u5c10\u516d\u6708"}, {"address": "rtmp://liveplay.guojianglive.com/live/9180_1063975", "img": "http://static.guojiang.tv/app/upload/2019_08_20/4566200ce098863a2986743fd1209688.jpg", "title": "\u7396\u513f%3F%3F%281956%29"}, {"address": "rtmp://liveplay.guojianglive.com/live/9180_963515", "img": "http://static.guojiang.tv/app/upload/2019_08_22/905d1c9e5009e49c487fefb7fafe0772.jpg", "title": "\u4e00%20\u4e00.%3F%3F"}, {"address": "rtmp://liveplay.guojianglive.com/live/9180_1253871", "img": "http://static.guojiang.tv/app/upload/2019_08_06/4b362c84a98bb6a4e04a9b9d26ed7fab.jpg", "title": "\u5b9d\u8d1dgirl"}, {"address": "rtmp://liveplay.guojianglive.com/live/9180_903985", "img": "http://static.guojiang.tv/app/upload/2019_07_24/3d4f1f0e512123c2afc54c8b1d0f4bbf.jpg", "title": "\u592a\u96be\u4e86."}, {"address": "rtmp://liveplay.guojianglive.com/live/9180_1123269", "img": "http://static.guojiang.tv/app/upload/2019_08_21/d3f4709c816fc9a149266edfbdf3ef5c.jpg", "title": "\u5c0f\u4e5d\u4e5d\u968f\u7f18"}, {"address": "rtmp://liveplay.guojianglive.com/live/9180_951922", "img": "http://static.guojiang.tv/app/upload/2019_04_01/f4ce7c19724e0c95044c9bb98edfe85d.jpg", "title": "\u8dd1\u8c03%3F%3F\u7409\u7483%3F%3F"}, {"address": "rtmp://liveplay.guojianglive.com/live/9180_1271145", "img": "http://static.guojiang.tv/app/upload/2019_08_21/35551dd34571f1d40799a6f244338ec5.jpg", "title": "Da%20mei"}, {"address": "rtmp://liveplay.guojianglive.com/live/9180_1234433", "img": "http://static.guojiang.tv/app/upload/2019_08_21/b66e76589e75ff656ee6a6e20875cff9.jpg", "title": "\u5b9d\u5b9d\u70ed\u6b4c\u5206\u4eab"}, {"address": "rtmp://liveplay.guojianglive.com/live/9180_1218536", "img": "http://static.guojiang.tv/app/upload/2019_08_12/d5ab70b139aa76395b96d2e4c6717c47.jpg", "title": "\u71d5\u5bf3\u513f%3F\u60f3\u8981\u4f60\u966a"}]}