{
"zhubo": [
{ "address":"http://wssource.pull.inke.cn/live/1566246724548832.flv?ikDnsOp=1&ikHost=ws&ikOp=0&codecInfo=8192&ikLog=1&ikChorus=1&dpSrc=-1&push_host=clsTrans.push.cls.inke.cn&msUid=&msSmid=","img":"http://img.ikstatic.cn/MTU2MjA5MjEzNjc5NiM2NjYjanBn.jpg","title":"\u6CFD%3F%3F%3F-Cynthia%3F%3F%3F%3F%3F%3F%3F%3F%3F%3F%3F%3F%3F%3F"},{ "address":"http://wssource.pull.inke.cn/live/1566240404105747.flv?ikDnsOp=1&ikHost=ws&ikOp=0&codecInfo=8192&ikLog=1&ikChorus=1&dpSrc=-1&push_host=clsTrans.push.cls.inke.cn&msUid=&msSmid=","img":"http://img.ikstatic.cn/MTU2MzQwMjA2OTY5OCMzMjEjanBn.jpg","title":"%3F%3F%20\u300C\u6734%20\u6734%20\u674E\u300D"},{ "address":"pzsp://temp.zigo.pull.inke.cn:8000/live/ld/trans/inkeaudio/mlinkm/1566241888885000?ikPath=1&dpSrc=-1&push_host=temp.zigo.link.inke.cn&msUid=&msSmid=","img":"http://img.ikstatic.cn/MTU2NjA0MTkwMTYwMCM2NzkjanBn.jpg","title":"\u4F9D\u4F9D%3F%3FR4"},{ "address":"http://rtazy.ke62w.cn/live/896803463_64f9f529a6fa7e46a020.flv","img":"http://img.ikstatic.cn/MTU2MTY1NDIyMzYyMCMxODIjanBn.jpg","title":"%3F%3F\u5A77\u5B50\u541B"},{ "address":"http://wssource.pull.inke.cn/live/1566242658240623.flv?ikDnsOp=1&ikHost=ws&ikOp=0&codecInfo=8192&ikLog=1&ikChorus=1&dpSrc=-1&push_host=clsTrans.push.cls.inke.cn&msUid=&msSmid=","img":"http://img.ikstatic.cn/MTU2NjIwMTA1NTU3MiMxODEjanBn.jpg","title":"\u6296\u795E%20%3F%3F"},{ "address":"http://wssource.pull.inke.cn/live/1566236271189678.flv?ikDnsOp=1&ikHost=ws&ikOp=0&codecInfo=8192&ikLog=1&ikChorus=1&dpSrc=-1&push_host=clsTrans.push.cls.inke.cn&msUid=&msSmid=","img":"http://img.ikstatic.cn/MTU2NjIxNTk0MDIyNSM4NzYjanBn.jpg","title":"\u5E03\u6717\u5C3C\u5C3C"},{ "address":"http://wssource.pull.inke.cn/live/1566242361298393.flv?ikDnsOp=1&ikHost=ws&ikOp=0&codecInfo=8192&ikLog=1&ikChorus=1&dpSrc=-1&push_host=clsTrans.push.cls.inke.cn&msUid=&msSmid=","img":"http://img.ikstatic.cn/MTU2NTYxNzMzMjcxNCM4NzQjanBn.jpg","title":"\u65B0\u5170%3F%3F\u3010\u6237\u5916\u5DE8\u661F\u3011%3F%3F"},{ "address":"http://pullws.styl555.com/live/be1b7ed242ae4cdf93c17788217a7121_480.flv","img":"https://p.best31w.com/public/attachment/201907/252331/1563622705963.png","title":"2019\u8D5E*\u5546\u3000\u3000\u3000\u3000\u3000\u3000\u3000\u300088"},{ "address":"http://pull.inke.cn/live/1566237243605305.flv?ikDnsOp=1&ikHost=ws&ikOp=0&codecInfo=8192&ikLog=1&dpSrc=-1&push_host=istream.inke.cn&msUid=&msSmid=","img":"http://img.ikstatic.cn/MTU1OTk1ODMzMjc1NiM0MjQjanBn.jpg","title":"\u7535\u5F71\u653E\u6620\u5385"},{ "address":"pzsp://temp.zigo.pull.inke.cn:8000/live/ld/trans/inkeaudio/mlinkm/1566243486654281?ikPath=1&dpSrc=-1&push_host=temp.zigo.link.inke.cn&msUid=&msSmid=","img":"http://img.ikstatic.cn/MTU2NjE1MjE1NjY3MSM4ODUjanBn.jpg","title":"\u67D2\u4E03"},{ "address":"pzsp://temp.zigo.pull.inke.cn:8000/live/ld/trans/inkeaudio/mlinkm/1566235139624204?ikPath=1&dpSrc=-1&push_host=temp.zigo.link.inke.cn&msUid=&msSmid=","img":"http://img.ikstatic.cn/MTU2MjI3NTI4MTU5OCM1ODMjanBn.jpg","title":"%3F%3F\u9F8D\u9053%3F%3F%20M.S.K%20%3F%3F"},{ "address":"pzsp://temp.zigo.pull.inke.cn:8000/live/ld/trans/inkeaudio/mlinkm/1566244938823423?ikPath=1&dpSrc=-1&push_host=temp.zigo.link.inke.cn&msUid=&msSmid=","img":"http://img.ikstatic.cn/MTU2NTg2MzY2NDc1MCMzNDcjanBn.jpg","title":"%3F\u5B89\u5B89%3F"},{ "address":"http://wssource.pull.inke.cn/live/1566240362637602.flv?ikDnsOp=1&ikHost=ws&ikOp=0&codecInfo=8192&ikLog=1&ikChorus=1&dpSrc=-1&push_host=clsTrans.push.cls.inke.cn&msUid=&msSmid=","img":"http://img.ikstatic.cn/MTU2NTI0NjUwNTY5NyM1OTgjanBn.jpg","title":"\u8D75\u516D\u516D"},{ "address":"http://wssource.pull.inke.cn/live/1566244256923019.flv?ikDnsOp=1&ikHost=ws&ikOp=0&codecInfo=8192&ikLog=1&ikChorus=1&dpSrc=-1&push_host=clsTrans.push.cls.inke.cn&msUid=&msSmid=","img":"http://img.ikstatic.cn/MTU2NTc4ODQ2MzIzNSMzNjgjanBn.jpg","title":"\u7136"},{ "address":"pzsp://temp.zigo.pull.inke.cn:8000/live/ld/trans/inkeaudio/mlinkm/1566243852986414?ikPath=1&dpSrc=-1&push_host=temp.zigo.link.inke.cn&msUid=&msSmid=","img":"http://img.ikstatic.cn/MTU2MDc1NzQ0NzQ0MyM3OTIjanBn.jpg","title":"\u5E38\u9752\u6811\uFF08\u5FC3\u7075\u7684\u5B81\u9759\uFF0C\u81F4\u8FDC\u7684\u751F\u6D3B\uFF09"},{ "address":"http://pull.inke.cn/live/1566224053596382.flv?ikDnsOp=1&ikHost=ws&ikOp=0&codecInfo=8192&ikLog=1&dpSrc=-1&push_host=istream.inke.cn&msUid=&msSmid=","img":"http://img.ikstatic.cn/MTU1NjI2NDg1NjE3NSMgOTIjanBn.jpg","title":"\u751C\u751C\u7684\u5FEB\u4E50%20\u5B8B\u6167\u4E54\u6D6A\u6F2B\u6EE1\u5C4B"},{ "address":"http://alisource.edge.inke.cn/live/1566246843322152.flv?ikDnsOp=1&ikHost=ali&ikOp=0&codecInfo=8192&ikLog=1&ikSyncBetaxyz=0&ikChorus=1&dpSrc=27&push_host=push.cls.inke.cn&msUid=&msSmid=","img":"http://img.ikstatic.cn/MTU0MzYxOTU4Njg3MSM1MTcjanBn.jpg","title":"\u68A6"}]
}